yl_xd_bigdate.py
yl_bigdate-1.0.dist-info/METADATA
yl_bigdate-1.0.dist-info/WHEEL
yl_bigdate-1.0.dist-info/top_level.txt
yl_bigdate-1.0.dist-info/RECORD
