Metadata-Version: 2.1
Name: yl-bigdate
Version: 1.0
Summary: bigdate
Home-page: UNKNOWN
Author: bigdate
Author-email: UNKNOWN
License: UNKNOWN
Platform: UNKNOWN
